pytest_divide_and_cover.py
pytest_divide_and_cover-0.5.1.dist-info/METADATA
pytest_divide_and_cover-0.5.1.dist-info/RECORD
pytest_divide_and_cover-0.5.1.dist-info/WHEEL
pytest_divide_and_cover-0.5.1.dist-info/entry_points.txt
pytest_divide_and_cover-0.5.1.dist-info/top_level.txt
