Metadata-Version: 2.1
Name: pytest-divide-and-cover
Version: 0.5.1
Summary: Picky test coverage for pytest
Home-page: UNKNOWN
Author: Max Woerner Chase
Author-email: max.chase@gmail.com
License: Apache 2.0
Keywords: coverage
Platform: UNKNOWN
Classifier: Development Status :: 7 - Inactive
Classifier: License :: OSI Approved :: Apache Software License
Classifier: Programming Language :: Python :: 3
Classifier: Programming Language :: Python :: 3.6
Classifier: Framework :: Pytest
Requires-Dist: divide-and-cover (>=0.4.0)
Requires-Dist: pytest (>=2.7.0)
